guessenc/__init__.py
guessenc-0.3.dist-info/LICENSE
guessenc-0.3.dist-info/METADATA
guessenc-0.3.dist-info/WHEEL
guessenc-0.3.dist-info/top_level.txt
guessenc-0.3.dist-info/RECORD
