Metadata-Version: 2.1
Name: guessenc
Version: 0.3
Summary: Infer HTML encoding from response headers & content
Home-page: https://github.com/bsolomon1124/guessenc
Author: Brad Solomon
Author-email: brad.solomon.1124@gmail.com
License: MIT
Keywords: encoding http html chardet detection
Platform: UNKNOWN
Classifier: Intended Audience :: Developers
Classifier: Development Status :: 3 - Alpha
Classifier: License :: OSI Approved :: MIT License
Classifier: Programming Language :: Python :: 3 :: Only
Classifier: Programming Language :: Python :: 3
Classifier: Programming Language :: Python :: 3.5
Classifier: Programming Language :: Python :: 3.6
Classifier: Programming Language :: Python :: 3.7
Classifier: Programming Language :: Python :: Implementation :: CPython
Requires-Python: >=3.5
Requires-Dist: lxml
Requires-Dist: chardet
